door/__init__.py
door/asyncio2.py
door/doors.py
door/multiprocessing2.py
door/primitives.py
door/py.typed
door/threading2.py
door/utilities.py
door/tests/__init__.py
door/tests/test_asyncio.py
door/tests/test_multiprocessing.py
door/tests/test_threading.py
door/tests/test_utilities.py
door-0.0.4.dist-info/LICENSE
door-0.0.4.dist-info/METADATA
door-0.0.4.dist-info/WHEEL
door-0.0.4.dist-info/top_level.txt
door-0.0.4.dist-info/RECORD
