Metadata-Version: 2.1
Name: door
Version: 0.0.4
Summary: A comprehensive python library for synchronization proxies
Home-page: https://github.com/blueskysolarracing/door
Author: Blue Sky Solar Racing
Author-email: blueskysolar@studentorg.utoronto.ca
License: MIT
Project-URL: Documentation, https://door.readthedocs.io/en/latest/
Project-URL: Source, https://github.com/blueskysolarracing/door
Project-URL: Tracker, https://github.com/blueskysolarracing/door/issues
Keywords: python,synchronization
Classifier: Development Status :: 5 - Production/Stable
Classifier: Intended Audience :: Developers
Classifier: Intended Audience :: Education
Classifier: Topic :: Education
Classifier: Topic :: Scientific/Engineering
Classifier: License :: OSI Approved :: MIT License
Classifier: Operating System :: OS Independent
Classifier: Programming Language :: Python
Classifier: Programming Language :: Python :: 3
Classifier: Programming Language :: Python :: 3 :: Only
Classifier: Programming Language :: Python :: 3.11
Classifier: Programming Language :: Python :: 3.12
Requires-Python: >=3.11
License-File: LICENSE
